{
    "10": {
        "disponibles": 12,
        "total": 19,
        "creneaux": 342
    },
    "20": {
        "disponibles": 4,
        "total": 8,
        "creneaux": 269
    },
    "09": {
        "disponibles": 0,
        "total": 0,
        "creneaux": 0
    },
    "21": {
        "disponibles": 0,
        "total": 0,
        "creneaux": 0
    },
    "13": {
        "disponibles": 0,
        "total": 0,
        "creneaux": 0
    },
    "23": {
        "disponibles": 0,
        "total": 0,
        "creneaux": 0
    },
    "06": {
        "disponibles": 22,
        "total": 52,
        "creneaux": 5930
    },
    "08": {
        "disponibles": 1,
        "total": 30,
        "creneaux": 75
    },
    "07": {
        "disponibles": 7,
        "total": 8,
        "creneaux": 4926
    },
    "25": {
        "disponibles": 0,
        "total": 0,
        "creneaux": 0
    },
    "12": {
        "disponibles": 17,
        "total": 37,
        "creneaux": 2702
    },
    "01": {
        "disponibles": 0,
        "total": 2,
        "creneaux": 0
    },
    "04": {
        "disponibles": 4,
        "total": 6,
        "creneaux": 5162
    },
    "03": {
        "disponibles": 0,
        "total": 0,
        "creneaux": 0
    },
    "17": {
        "disponibles": 0,
        "total": 0,
        "creneaux": 0
    },
    "24": {
        "disponibles": 0,
        "total": 4,
        "creneaux": 0
    },
    "22": {
        "disponibles": 3,
        "total": 19,
        "creneaux": 2440
    },
    "19": {
        "disponibles": 0,
        "total": 0,
        "creneaux": 0
    },
    "14": {
        "disponibles": 2,
        "total": 109,
        "creneaux": 55
    },
    "18": {
        "disponibles": 0,
        "total": 5,
        "creneaux": 0
    },
    "05": {
        "disponibles": 13,
        "total": 40,
        "creneaux": 2283
    },
    "tout_departement": {
        "disponibles": 85,
        "total": 339,
        "creneaux": 24184
    }
}