{
    "10": {
        "disponibles": 0,
        "total": 19,
        "creneaux": 0
    },
    "20": {
        "disponibles": 6,
        "total": 8,
        "creneaux": 1433
    },
    "09": {
        "disponibles": 0,
        "total": 0,
        "creneaux": 0
    },
    "21": {
        "disponibles": 0,
        "total": 0,
        "creneaux": 0
    },
    "13": {
        "disponibles": 0,
        "total": 0,
        "creneaux": 0
    },
    "23": {
        "disponibles": 0,
        "total": 0,
        "creneaux": 0
    },
    "06": {
        "disponibles": 23,
        "total": 52,
        "creneaux": 3158
    },
    "08": {
        "disponibles": 4,
        "total": 30,
        "creneaux": 5757
    },
    "07": {
        "disponibles": 6,
        "total": 7,
        "creneaux": 1430
    },
    "25": {
        "disponibles": 0,
        "total": 0,
        "creneaux": 0
    },
    "12": {
        "disponibles": 15,
        "total": 37,
        "creneaux": 5653
    },
    "01": {
        "disponibles": 0,
        "total": 2,
        "creneaux": 0
    },
    "04": {
        "disponibles": 5,
        "total": 6,
        "creneaux": 4441
    },
    "03": {
        "disponibles": 0,
        "total": 0,
        "creneaux": 0
    },
    "17": {
        "disponibles": 0,
        "total": 0,
        "creneaux": 0
    },
    "24": {
        "disponibles": 6,
        "total": 48,
        "creneaux": 698
    },
    "22": {
        "disponibles": 5,
        "total": 22,
        "creneaux": 12606
    },
    "19": {
        "disponibles": 10,
        "total": 15,
        "creneaux": 0
    },
    "14": {
        "disponibles": 15,
        "total": 164,
        "creneaux": 1844
    },
    "18": {
        "disponibles": 3,
        "total": 5,
        "creneaux": 193
    },
    "05": {
        "disponibles": 0,
        "total": 0,
        "creneaux": 0
    },
    "tout_departement": {
        "disponibles": 98,
        "total": 415,
        "creneaux": 37213
    }
}