{
    "10": {
        "disponibles": 16,
        "total": 19,
        "creneaux": 723
    },
    "20": {
        "disponibles": 8,
        "total": 8,
        "creneaux": 8765
    },
    "09": {
        "disponibles": 0,
        "total": 0,
        "creneaux": 0
    },
    "21": {
        "disponibles": 0,
        "total": 0,
        "creneaux": 0
    },
    "13": {
        "disponibles": 0,
        "total": 0,
        "creneaux": 0
    },
    "23": {
        "disponibles": 0,
        "total": 0,
        "creneaux": 0
    },
    "06": {
        "disponibles": 31,
        "total": 52,
        "creneaux": 7560
    },
    "08": {
        "disponibles": 31,
        "total": 42,
        "creneaux": 12435
    },
    "07": {
        "disponibles": 4,
        "total": 7,
        "creneaux": 1602
    },
    "25": {
        "disponibles": 0,
        "total": 0,
        "creneaux": 0
    },
    "12": {
        "disponibles": 33,
        "total": 39,
        "creneaux": 20478
    },
    "01": {
        "disponibles": 0,
        "total": 0,
        "creneaux": 0
    },
    "04": {
        "disponibles": 4,
        "total": 8,
        "creneaux": 25660
    },
    "03": {
        "disponibles": 0,
        "total": 0,
        "creneaux": 0
    },
    "17": {
        "disponibles": 0,
        "total": 0,
        "creneaux": 0
    },
    "24": {
        "disponibles": 28,
        "total": 47,
        "creneaux": 1540
    },
    "22": {
        "disponibles": 4,
        "total": 19,
        "creneaux": 876
    },
    "19": {
        "disponibles": 13,
        "total": 15,
        "creneaux": 9
    },
    "14": {
        "disponibles": 125,
        "total": 159,
        "creneaux": 73443
    },
    "18": {
        "disponibles": 5,
        "total": 5,
        "creneaux": 2432
    },
    "05": {
        "disponibles": 0,
        "total": 0,
        "creneaux": 0
    },
    "tout_departement": {
        "disponibles": 302,
        "total": 420,
        "creneaux": 155523
    }
}