{
    "10": {
        "disponibles": 18,
        "total": 19,
        "creneaux": 1104
    },
    "20": {
        "disponibles": 3,
        "total": 8,
        "creneaux": 1300
    },
    "09": {
        "disponibles": 0,
        "total": 0,
        "creneaux": 0
    },
    "21": {
        "disponibles": 0,
        "total": 0,
        "creneaux": 0
    },
    "13": {
        "disponibles": 0,
        "total": 0,
        "creneaux": 0
    },
    "23": {
        "disponibles": 0,
        "total": 0,
        "creneaux": 0
    },
    "06": {
        "disponibles": 31,
        "total": 52,
        "creneaux": 4997
    },
    "08": {
        "disponibles": 7,
        "total": 42,
        "creneaux": 11726
    },
    "07": {
        "disponibles": 4,
        "total": 7,
        "creneaux": 2146
    },
    "25": {
        "disponibles": 0,
        "total": 0,
        "creneaux": 0
    },
    "12": {
        "disponibles": 33,
        "total": 39,
        "creneaux": 29295
    },
    "01": {
        "disponibles": 0,
        "total": 0,
        "creneaux": 0
    },
    "04": {
        "disponibles": 4,
        "total": 8,
        "creneaux": 28015
    },
    "03": {
        "disponibles": 0,
        "total": 0,
        "creneaux": 0
    },
    "17": {
        "disponibles": 0,
        "total": 0,
        "creneaux": 0
    },
    "24": {
        "disponibles": 23,
        "total": 54,
        "creneaux": 1612
    },
    "22": {
        "disponibles": 5,
        "total": 19,
        "creneaux": 2755
    },
    "19": {
        "disponibles": 16,
        "total": 16,
        "creneaux": 39
    },
    "14": {
        "disponibles": 111,
        "total": 159,
        "creneaux": 12319
    },
    "18": {
        "disponibles": 5,
        "total": 5,
        "creneaux": 1274
    },
    "05": {
        "disponibles": 0,
        "total": 0,
        "creneaux": 0
    },
    "tout_departement": {
        "disponibles": 260,
        "total": 428,
        "creneaux": 96582
    }
}