{
    "10": {
        "disponibles": 14,
        "total": 19,
        "creneaux": 521
    },
    "20": {
        "disponibles": 6,
        "total": 8,
        "creneaux": 2485
    },
    "09": {
        "disponibles": 0,
        "total": 0,
        "creneaux": 0
    },
    "21": {
        "disponibles": 0,
        "total": 0,
        "creneaux": 0
    },
    "13": {
        "disponibles": 0,
        "total": 0,
        "creneaux": 0
    },
    "23": {
        "disponibles": 0,
        "total": 0,
        "creneaux": 0
    },
    "06": {
        "disponibles": 21,
        "total": 52,
        "creneaux": 2307
    },
    "08": {
        "disponibles": 16,
        "total": 42,
        "creneaux": 2692
    },
    "07": {
        "disponibles": 4,
        "total": 7,
        "creneaux": 1496
    },
    "25": {
        "disponibles": 0,
        "total": 0,
        "creneaux": 0
    },
    "12": {
        "disponibles": 25,
        "total": 39,
        "creneaux": 43532
    },
    "01": {
        "disponibles": 0,
        "total": 0,
        "creneaux": 0
    },
    "04": {
        "disponibles": 4,
        "total": 8,
        "creneaux": 10026
    },
    "03": {
        "disponibles": 0,
        "total": 0,
        "creneaux": 0
    },
    "17": {
        "disponibles": 0,
        "total": 0,
        "creneaux": 0
    },
    "24": {
        "disponibles": 10,
        "total": 55,
        "creneaux": 1294
    },
    "22": {
        "disponibles": 3,
        "total": 19,
        "creneaux": 1084
    },
    "19": {
        "disponibles": 12,
        "total": 16,
        "creneaux": 0
    },
    "14": {
        "disponibles": 115,
        "total": 163,
        "creneaux": 4602
    },
    "18": {
        "disponibles": 5,
        "total": 5,
        "creneaux": 420
    },
    "05": {
        "disponibles": 0,
        "total": 0,
        "creneaux": 0
    },
    "tout_departement": {
        "disponibles": 235,
        "total": 433,
        "creneaux": 70459
    }
}