{
    "10": {
        "disponibles": 14,
        "total": 19,
        "creneaux": 588
    },
    "20": {
        "disponibles": 8,
        "total": 8,
        "creneaux": 967
    },
    "09": {
        "disponibles": 0,
        "total": 0,
        "creneaux": 0
    },
    "21": {
        "disponibles": 0,
        "total": 0,
        "creneaux": 0
    },
    "13": {
        "disponibles": 0,
        "total": 0,
        "creneaux": 0
    },
    "23": {
        "disponibles": 0,
        "total": 0,
        "creneaux": 0
    },
    "06": {
        "disponibles": 24,
        "total": 52,
        "creneaux": 3435
    },
    "08": {
        "disponibles": 6,
        "total": 42,
        "creneaux": 11637
    },
    "07": {
        "disponibles": 4,
        "total": 7,
        "creneaux": 2366
    },
    "25": {
        "disponibles": 0,
        "total": 0,
        "creneaux": 0
    },
    "12": {
        "disponibles": 32,
        "total": 39,
        "creneaux": 31668
    },
    "01": {
        "disponibles": 0,
        "total": 0,
        "creneaux": 0
    },
    "04": {
        "disponibles": 4,
        "total": 8,
        "creneaux": 26845
    },
    "03": {
        "disponibles": 0,
        "total": 0,
        "creneaux": 0
    },
    "17": {
        "disponibles": 0,
        "total": 0,
        "creneaux": 0
    },
    "24": {
        "disponibles": 13,
        "total": 55,
        "creneaux": 870
    },
    "22": {
        "disponibles": 6,
        "total": 19,
        "creneaux": 2252
    },
    "19": {
        "disponibles": 15,
        "total": 16,
        "creneaux": 108
    },
    "14": {
        "disponibles": 108,
        "total": 161,
        "creneaux": 24424
    },
    "18": {
        "disponibles": 5,
        "total": 5,
        "creneaux": 1084
    },
    "05": {
        "disponibles": 0,
        "total": 0,
        "creneaux": 0
    },
    "tout_departement": {
        "disponibles": 239,
        "total": 431,
        "creneaux": 106244
    }
}