{
    "10": {
        "disponibles": 10,
        "total": 19,
        "creneaux": 579
    },
    "20": {
        "disponibles": 8,
        "total": 8,
        "creneaux": 3930
    },
    "09": {
        "disponibles": 0,
        "total": 0,
        "creneaux": 0
    },
    "21": {
        "disponibles": 0,
        "total": 0,
        "creneaux": 0
    },
    "13": {
        "disponibles": 0,
        "total": 0,
        "creneaux": 0
    },
    "23": {
        "disponibles": 0,
        "total": 0,
        "creneaux": 0
    },
    "06": {
        "disponibles": 15,
        "total": 52,
        "creneaux": 2186
    },
    "08": {
        "disponibles": 5,
        "total": 42,
        "creneaux": 1642
    },
    "07": {
        "disponibles": 3,
        "total": 7,
        "creneaux": 744
    },
    "25": {
        "disponibles": 0,
        "total": 0,
        "creneaux": 0
    },
    "12": {
        "disponibles": 27,
        "total": 39,
        "creneaux": 29931
    },
    "01": {
        "disponibles": 0,
        "total": 0,
        "creneaux": 0
    },
    "04": {
        "disponibles": 4,
        "total": 8,
        "creneaux": 9278
    },
    "03": {
        "disponibles": 0,
        "total": 0,
        "creneaux": 0
    },
    "17": {
        "disponibles": 0,
        "total": 0,
        "creneaux": 0
    },
    "24": {
        "disponibles": 13,
        "total": 55,
        "creneaux": 2922
    },
    "22": {
        "disponibles": 6,
        "total": 19,
        "creneaux": 878
    },
    "19": {
        "disponibles": 14,
        "total": 16,
        "creneaux": 48
    },
    "14": {
        "disponibles": 14,
        "total": 164,
        "creneaux": 1006
    },
    "18": {
        "disponibles": 5,
        "total": 5,
        "creneaux": 793
    },
    "05": {
        "disponibles": 0,
        "total": 0,
        "creneaux": 0
    },
    "tout_departement": {
        "disponibles": 124,
        "total": 434,
        "creneaux": 53937
    }
}